MANIFEST.in
setup.py
slth/__init__.py
slth/application.py
slth/apps.py
slth/components.py
slth/exceptions.py
slth/factory.py
slth/forms.py
slth/models.py
slth/notifications.py
slth/oauth.py
slth/permissions.py
slth/printer.py
slth/queryset.py
slth/roles.py
slth/serializer.py
slth/statistics.py
slth/tasks.py
slth/tests.py
slth/threadlocal.py
slth/timezone.py
slth/urls.py
slth/utils.py
slth/views.py
slth/cmd/configure/__main__.py
slth/cmd/init/__main__.py
slth/cmd/init/__pycache__/__main__.cpython-312.pyc
slth/cmd/init/boilerplate/.DS_Store
slth/cmd/init/boilerplate/.gitignore
slth/cmd/init/boilerplate/base.env
slth/cmd/init/boilerplate/docker-compose.yml
slth/cmd/init/boilerplate/local.env
slth/cmd/init/boilerplate/run.sh
slth/cmd/init/boilerplate/test.sh
slth/cmd/init/boilerplate/backend/entrypoint.sh
slth/cmd/init/boilerplate/backend/manage.py
slth/cmd/init/boilerplate/backend/requirements.txt
slth/cmd/init/boilerplate/backend/api/__init__.py
slth/cmd/init/boilerplate/backend/api/asgi.py
slth/cmd/init/boilerplate/backend/api/models.py
slth/cmd/init/boilerplate/backend/api/settings.py
slth/cmd/init/boilerplate/backend/api/tests.py
slth/cmd/init/boilerplate/backend/api/urls.py
slth/cmd/init/boilerplate/backend/api/wsgi.py
slth/cmd/init/boilerplate/backend/api/endpoints/__init__.py
slth/cmd/init/boilerplate/frontend/package.json
slth/cmd/init/boilerplate/frontend/vite.config.js
slth/cmd/init/boilerplate/frontend/src/main.jsx
slth/cmd/init/boilerplate/selenium/run.sh
slth/db/__init__.py
slth/db/generic.py
slth/db/models.py
slth/endpoints/__init__.py
slth/endpoints/auth.py
slth/endpoints/deletion.py
slth/endpoints/dev.py
slth/endpoints/email.py
slth/endpoints/job.py
slth/endpoints/log.py
slth/endpoints/profile.py
slth/endpoints/pushsubscription.py
slth/endpoints/report.py
slth/endpoints/role.py
slth/endpoints/settings.py
slth/endpoints/task.py
slth/endpoints/timezone.py
slth/endpoints/user.py
slth/endpoints/whatsappnotification.py
slth/geo/__init__.py
slthcore.egg-info/PKG-INFO
slthcore.egg-info/SOURCES.txt
slthcore.egg-info/dependency_links.txt
slthcore.egg-info/top_level.txt